HISTORY.rst
LICENSE
MANIFEST.in
README.rst
setup.cfg
setup.py
bin/fsbck.py
docs/Makefile
docs/make.bat
docs/build/doctrees/command_usage.doctree
docs/build/doctrees/config_files.doctree
docs/build/doctrees/database_structure.doctree
docs/build/doctrees/environment.pickle
docs/build/doctrees/index.doctree
docs/build/doctrees/observations.doctree
docs/build/doctrees/todo.doctree
docs/build/doctrees/volume_content.doctree
docs/build/doctrees/warnings.doctree
docs/build/html/.buildinfo
docs/build/html/command_usage.html
docs/build/html/config_files.html
docs/build/html/database_structure.html
docs/build/html/genindex.html
docs/build/html/index.html
docs/build/html/objects.inv
docs/build/html/observations.html
docs/build/html/py-modindex.html
docs/build/html/search.html
docs/build/html/searchindex.js
docs/build/html/todo.html
docs/build/html/volume_content.html
docs/build/html/warnings.html
docs/build/html/_images/reportfiles_screenshot.png
docs/build/html/_images/volume_screenshot.png
docs/build/html/_sources/command_usage.rst.txt
docs/build/html/_sources/config_files.rst.txt
docs/build/html/_sources/database_structure.rst.txt
docs/build/html/_sources/index.rst.txt
docs/build/html/_sources/observations.rst.txt
docs/build/html/_sources/todo.rst.txt
docs/build/html/_sources/volume_content.rst.txt
docs/build/html/_sources/warnings.rst.txt
docs/build/html/_static/ajax-loader.gif
docs/build/html/_static/alabaster.css
docs/build/html/_static/basic.css
docs/build/html/_static/comment-bright.png
docs/build/html/_static/comment-close.png
docs/build/html/_static/comment.png
docs/build/html/_static/custom.css
docs/build/html/_static/doctools.js
docs/build/html/_static/down-pressed.png
docs/build/html/_static/down.png
docs/build/html/_static/file.png
docs/build/html/_static/jquery-3.1.0.js
docs/build/html/_static/jquery.js
docs/build/html/_static/minus.png
docs/build/html/_static/plus.png
docs/build/html/_static/pygments.css
docs/build/html/_static/searchtools.js
fsbackup.egg-info/PKG-INFO
fsbackup.egg-info/SOURCES.txt
fsbackup.egg-info/dependency_links.txt
fsbackup.egg-info/not-zip-safe
fsbackup.egg-info/requires.txt
fsbackup.egg-info/top_level.txt
