Metadata-Version: 1.1
Name: fsbackup
Version: 0.2.1
Summary: Multi-Volume Backup for Large Filesystems
Home-page: https://github.com/zeycus/fsbackup/
Author: Miguel Garcia (aka Zeycus)
Author-email: zeycus@gmail.com
License: MIT
Keywords: backup volume
Platform: UNKNOWN
Classifier: Development Status :: 4 - Beta
Classifier: License :: OSI Approved :: MIT License
Classifier: Programming Language :: Python :: 3.5
Classifier: Topic :: System :: Archiving :: Backup
